LICENSE
README.md
setup.py
NGram/AdditiveSmoothing.py
NGram/GoodTuringSmoothing.py
NGram/InterpolatedSmoothing.py
NGram/LaplaceSmoothing.py
NGram/MultipleFile.py
NGram/NGram.py
NGram/NGramNode.py
NGram/NoSmoothing.py
NGram/NoSmoothingWithDictionary.py
NGram/NoSmoothingWithNonRareWords.py
NGram/SimpleSmoothing.py
NGram/TrainedSmoothing.py
NGram/__init__.py
NlpToolkit_NGram.egg-info/PKG-INFO
NlpToolkit_NGram.egg-info/SOURCES.txt
NlpToolkit_NGram.egg-info/dependency_links.txt
NlpToolkit_NGram.egg-info/requires.txt
NlpToolkit_NGram.egg-info/top_level.txt
test/AdditiveSmoothingTest.py
test/CorpusTest.py
test/GoodTuringSmoothingTest.py
test/InterpolatedSmoothingTest.py
test/LaplaceSmoothingTest.py
test/NGramTest.py
test/NoSmoothingTest.py
test/SimpleSmoothingTest.py
test/__init__.py