Metadata-Version: 2.1
Name: NlpToolkit-NGram
Version: 1.0.18
Summary: NGram library
Home-page: https://github.com/StarlangSoftware/NGram-Py
Author: olcaytaner
Author-email: olcay.yildiz@ozyegin.edu.tr
License: UNKNOWN
Platform: UNKNOWN
License-File: LICENSE
